replete/__init__.py
replete/abc.py
replete/aio.py
replete/cli.py
replete/consistent_hash.py
replete/datetime.py
replete/enum.py
replete/flock.py
replete/funcutils.py
replete/logging.py
replete/register.py
replete/testing.py
replete/timing.py
replete/utils.py
replete-2.3.2.dist-info/entry_points.txt
replete-2.3.2.dist-info/LICENSE
replete-2.3.2.dist-info/WHEEL
replete-2.3.2.dist-info/METADATA
replete-2.3.2.dist-info/RECORD
