Metadata-Version: 2.1
Name: replete
Version: 2.3.2
Summary: Assorted utilities with minimal dependencies
Author: Anton Vasilev, Artem Vasenin
Maintainer-email: Artem Vasenin <vasart169@gmail.com>
Requires-Python: >=3.10
Requires-Dist: coloredlogs
Requires-Dist: docstring-parser
Requires-Dist: python-dateutil
Requires-Dist: xxhash
Requires-Dist: black ; extra == "dev"
Requires-Dist: isort ; extra == "dev"
Requires-Dist: replete[test] ; extra == "dev"
Requires-Dist: ruff ; extra == "dev"
Requires-Dist: flaky ; extra == "test"
Requires-Dist: pytest ; extra == "test"
Requires-Dist: pytest-asyncio ; extra == "test"
Requires-Dist: pytest-coverage ; extra == "test"
Requires-Dist: replete[testing] ; extra == "test"
Requires-Dist: types-python-dateutil ; extra == "test"
Requires-Dist: types-xxhash ; extra == "test"
Requires-Dist: pytest<8 ; extra == "testing"
Requires-Dist: pyyaml ; extra == "testing"
Provides-Extra: dev
Provides-Extra: test
Provides-Extra: testing
